<?xml version="1.0" encoding="utf-8"?>
<SoundBanksInfo Platform="Windows" BasePlatform="Windows" SchemaVersion="10" SoundbankVersion="113">
	<RootPaths>
		<ProjectRoot>F:\Tanks Projects\RelHaxSoundMod\ingame voice\Base Pack\RelHaxCen\RelHax_3\</ProjectRoot>
		<SourceFilesRoot>F:\Tanks Projects\RelHaxSoundMod\ingame voice\Base Pack\RelHaxCen\RelHax_3\.cache\Windows\</SourceFilesRoot>
		<SoundBanksRoot>F:\Tanks Projects\RelHaxSoundMod\ingame voice\Base Pack\RelHaxCen\RelHax_3\GeneratedSoundBanks\Windows\</SoundBanksRoot>
		<ExternalSourcesInputFile></ExternalSourcesInputFile>
		<ExternalSourcesOutputRoot>F:\Tanks Projects\RelHaxSoundMod\ingame voice\Base Pack\RelHaxCen\RelHax_3\GeneratedSoundBanks\Windows\</ExternalSourcesOutputRoot>
	</RootPaths>
	<DialogueEvents/>
	<StreamedFiles/>
	<MediaFilesNotInAnyBank/>
	<SoundBanks>
		<SoundBank Id="1355168291" Language="SFX">
			<ShortName>Init</ShortName>
			<Path>Init.bnk</Path>
		</SoundBank>
		<SoundBank Id="3135547431" Language="English(UK)">
			<ShortName>RelHax_3</ShortName>
			<Path>English(UK)\RelHax_3.bnk</Path>
			<IncludedEvents>
				<Event Id="3928775652" Name="vo_radioman_killed"/>
				<Event Id="590598450" Name="vo_start_battle"/>
				<Event Id="2775977275" Name="vo_surveying_devices_damaged"/>
				<Event Id="1112395295" Name="vo_surveying_devices_destroyed"/>
				<Event Id="998311689" Name="vo_surveying_devices_functional"/>
			</IncludedEvents>
			<IncludedMemoryFiles>
				<File Id="7333443" Language="English(UK)">
					<ShortName>start_battle_21.wav</ShortName>
					<Path>Voices\English(UK)\start_battle_21_E843A46D.wem</Path>
				</File>
				<File Id="7540519" Language="English(UK)">
					<ShortName>start_battle_04.wav</ShortName>
					<Path>Voices\English(UK)\start_battle_04_E843A46D.wem</Path>
				</File>
				<File Id="36433349" Language="English(UK)">
					<ShortName>surveying_devices_functional_10.wav</ShortName>
					<Path>Voices\English(UK)\surveying_devices_functional_10_E843A46D.wem</Path>
				</File>
				<File Id="38345785" Language="English(UK)">
					<ShortName>surveying_devices_damaged_07.wav</ShortName>
					<Path>Voices\English(UK)\surveying_devices_damaged_07_E843A46D.wem</Path>
				</File>
				<File Id="41472027" Language="English(UK)">
					<ShortName>surveying_devices_destroyed_07.wav</ShortName>
					<Path>Voices\English(UK)\surveying_devices_destroyed_07_E843A46D.wem</Path>
				</File>
				<File Id="42449756" Language="English(UK)">
					<ShortName>start_battle_13.wav</ShortName>
					<Path>Voices\English(UK)\start_battle_13_E843A46D.wem</Path>
				</File>
				<File Id="89112948" Language="English(UK)">
					<ShortName>surveying_devices_functional_02.wav</ShortName>
					<Path>Voices\English(UK)\surveying_devices_functional_02_E843A46D.wem</Path>
				</File>
				<File Id="111948707" Language="English(UK)">
					<ShortName>surveying_devices_functional_11.wav</ShortName>
					<Path>Voices\English(UK)\surveying_devices_functional_11_E843A46D.wem</Path>
				</File>
				<File Id="126641396" Language="English(UK)">
					<ShortName>start_battle_32.wav</ShortName>
					<Path>Voices\English(UK)\start_battle_32_E843A46D.wem</Path>
				</File>
				<File Id="146360394" Language="English(UK)">
					<ShortName>start_battle_33.wav</ShortName>
					<Path>Voices\English(UK)\start_battle_33_E843A46D.wem</Path>
				</File>
				<File Id="173539092" Language="English(UK)">
					<ShortName>start_battle_36.wav</ShortName>
					<Path>Voices\English(UK)\start_battle_36_E843A46D.wem</Path>
				</File>
				<File Id="176393282" Language="English(UK)">
					<ShortName>start_battle_31.wav</ShortName>
					<Path>Voices\English(UK)\start_battle_31_E843A46D.wem</Path>
				</File>
				<File Id="181578495" Language="English(UK)">
					<ShortName>radioman_killed_01.wav</ShortName>
					<Path>Voices\English(UK)\radioman_killed_01_E843A46D.wem</Path>
				</File>
				<File Id="183309385" Language="English(UK)">
					<ShortName>start_battle_10.wav</ShortName>
					<Path>Voices\English(UK)\start_battle_10_E843A46D.wem</Path>
				</File>
				<File Id="246892649" Language="English(UK)">
					<ShortName>start_battle_29.wav</ShortName>
					<Path>Voices\English(UK)\start_battle_29_E843A46D.wem</Path>
				</File>
				<File Id="248238914" Language="English(UK)">
					<ShortName>surveying_devices_functional_03.wav</ShortName>
					<Path>Voices\English(UK)\surveying_devices_functional_03_E843A46D.wem</Path>
				</File>
				<File Id="257174305" Language="English(UK)">
					<ShortName>surveying_devices_damaged_02.wav</ShortName>
					<Path>Voices\English(UK)\surveying_devices_damaged_02_E843A46D.wem</Path>
				</File>
				<File Id="271332506" Language="English(UK)">
					<ShortName>surveying_devices_destroyed_09.wav</ShortName>
					<Path>Voices\English(UK)\surveying_devices_destroyed_09_E843A46D.wem</Path>
				</File>
				<File Id="271632648" Language="English(UK)">
					<ShortName>start_battle_15.wav</ShortName>
					<Path>Voices\English(UK)\start_battle_15_E843A46D.wem</Path>
				</File>
				<File Id="276822609" Language="English(UK)">
					<ShortName>radioman_killed_03.wav</ShortName>
					<Path>Voices\English(UK)\radioman_killed_03_E843A46D.wem</Path>
				</File>
				<File Id="278921024" Language="English(UK)">
					<ShortName>start_battle_45.wav</ShortName>
					<Path>Voices\English(UK)\start_battle_45_E843A46D.wem</Path>
				</File>
				<File Id="282368329" Language="English(UK)">
					<ShortName>start_battle_42.wav</ShortName>
					<Path>Voices\English(UK)\start_battle_42_E843A46D.wem</Path>
				</File>
				<File Id="306292629" Language="English(UK)">
					<ShortName>start_battle_51.wav</ShortName>
					<Path>Voices\English(UK)\start_battle_51_E843A46D.wem</Path>
				</File>
				<File Id="311948292" Language="English(UK)">
					<ShortName>surveying_devices_destroyed_03.wav</ShortName>
					<Path>Voices\English(UK)\surveying_devices_destroyed_03_E843A46D.wem</Path>
				</File>
				<File Id="313454371" Language="English(UK)">
					<ShortName>surveying_devices_destroyed_01.wav</ShortName>
					<Path>Voices\English(UK)\surveying_devices_destroyed_01_E843A46D.wem</Path>
				</File>
				<File Id="318451038" Language="English(UK)">
					<ShortName>start_battle_46.wav</ShortName>
					<Path>Voices\English(UK)\start_battle_46_E843A46D.wem</Path>
				</File>
				<File Id="319960662" Language="English(UK)">
					<ShortName>start_battle_55.wav</ShortName>
					<Path>Voices\English(UK)\start_battle_55_E843A46D.wem</Path>
				</File>
				<File Id="328084280" Language="English(UK)">
					<ShortName>surveying_devices_destroyed_02.wav</ShortName>
					<Path>Voices\English(UK)\surveying_devices_destroyed_02_E843A46D.wem</Path>
				</File>
				<File Id="332320911" Language="English(UK)">
					<ShortName>start_battle_27.wav</ShortName>
					<Path>Voices\English(UK)\start_battle_27_E843A46D.wem</Path>
				</File>
				<File Id="350287854" Language="English(UK)">
					<ShortName>surveying_devices_functional_01.wav</ShortName>
					<Path>Voices\English(UK)\surveying_devices_functional_01_E843A46D.wem</Path>
				</File>
				<File Id="351778611" Language="English(UK)">
					<ShortName>start_battle_43.wav</ShortName>
					<Path>Voices\English(UK)\start_battle_43_E843A46D.wem</Path>
				</File>
				<File Id="353774309" Language="English(UK)">
					<ShortName>surveying_devices_damaged_06.wav</ShortName>
					<Path>Voices\English(UK)\surveying_devices_damaged_06_E843A46D.wem</Path>
				</File>
				<File Id="355529635" Language="English(UK)">
					<ShortName>start_battle_07.wav</ShortName>
					<Path>Voices\English(UK)\start_battle_07_E843A46D.wem</Path>
				</File>
				<File Id="357123562" Language="English(UK)">
					<ShortName>surveying_devices_functional_05.wav</ShortName>
					<Path>Voices\English(UK)\surveying_devices_functional_05_E843A46D.wem</Path>
				</File>
				<File Id="398379140" Language="English(UK)">
					<ShortName>surveying_devices_destroyed_06.wav</ShortName>
					<Path>Voices\English(UK)\surveying_devices_destroyed_06_E843A46D.wem</Path>
				</File>
				<File Id="404792107" Language="English(UK)">
					<ShortName>start_battle_05.wav</ShortName>
					<Path>Voices\English(UK)\start_battle_05_E843A46D.wem</Path>
				</File>
				<File Id="413595419" Language="English(UK)">
					<ShortName>start_battle_25.wav</ShortName>
					<Path>Voices\English(UK)\start_battle_25_E843A46D.wem</Path>
				</File>
				<File Id="426072268" Language="English(UK)">
					<ShortName>surveying_devices_damaged_08.wav</ShortName>
					<Path>Voices\English(UK)\surveying_devices_damaged_08_E843A46D.wem</Path>
				</File>
				<File Id="429840941" Language="English(UK)">
					<ShortName>start_battle_39.wav</ShortName>
					<Path>Voices\English(UK)\start_battle_39_E843A46D.wem</Path>
				</File>
				<File Id="432135941" Language="English(UK)">
					<ShortName>start_battle_47.wav</ShortName>
					<Path>Voices\English(UK)\start_battle_47_E843A46D.wem</Path>
				</File>
				<File Id="454775431" Language="English(UK)">
					<ShortName>start_battle_19.wav</ShortName>
					<Path>Voices\English(UK)\start_battle_19_E843A46D.wem</Path>
				</File>
				<File Id="455207258" Language="English(UK)">
					<ShortName>start_battle_16.wav</ShortName>
					<Path>Voices\English(UK)\start_battle_16_E843A46D.wem</Path>
				</File>
				<File Id="457061953" Language="English(UK)">
					<ShortName>start_battle_34.wav</ShortName>
					<Path>Voices\English(UK)\start_battle_34_E843A46D.wem</Path>
				</File>
				<File Id="467157231" Language="English(UK)">
					<ShortName>start_battle_12.wav</ShortName>
					<Path>Voices\English(UK)\start_battle_12_E843A46D.wem</Path>
				</File>
				<File Id="470463046" Language="English(UK)">
					<ShortName>surveying_devices_destroyed_04.wav</ShortName>
					<Path>Voices\English(UK)\surveying_devices_destroyed_04_E843A46D.wem</Path>
				</File>
				<File Id="493474816" Language="English(UK)">
					<ShortName>surveying_devices_damaged_04.wav</ShortName>
					<Path>Voices\English(UK)\surveying_devices_damaged_04_E843A46D.wem</Path>
				</File>
				<File Id="504075905" Language="English(UK)">
					<ShortName>surveying_devices_damaged_03.wav</ShortName>
					<Path>Voices\English(UK)\surveying_devices_damaged_03_E843A46D.wem</Path>
				</File>
				<File Id="528284343" Language="English(UK)">
					<ShortName>start_battle_24.wav</ShortName>
					<Path>Voices\English(UK)\start_battle_24_E843A46D.wem</Path>
				</File>
				<File Id="533608475" Language="English(UK)">
					<ShortName>start_battle_35.wav</ShortName>
					<Path>Voices\English(UK)\start_battle_35_E843A46D.wem</Path>
				</File>
				<File Id="565442456" Language="English(UK)">
					<ShortName>start_battle_03.wav</ShortName>
					<Path>Voices\English(UK)\start_battle_03_E843A46D.wem</Path>
				</File>
				<File Id="586185533" Language="English(UK)">
					<ShortName>surveying_devices_damaged_01.wav</ShortName>
					<Path>Voices\English(UK)\surveying_devices_damaged_01_E843A46D.wem</Path>
				</File>
				<File Id="586801654" Language="English(UK)">
					<ShortName>start_battle_08.wav</ShortName>
					<Path>Voices\English(UK)\start_battle_08_E843A46D.wem</Path>
				</File>
				<File Id="590114360" Language="English(UK)">
					<ShortName>start_battle_50.wav</ShortName>
					<Path>Voices\English(UK)\start_battle_50_E843A46D.wem</Path>
				</File>
				<File Id="590641722" Language="English(UK)">
					<ShortName>start_battle_53.wav</ShortName>
					<Path>Voices\English(UK)\start_battle_53_E843A46D.wem</Path>
				</File>
				<File Id="591611362" Language="English(UK)">
					<ShortName>start_battle_23.wav</ShortName>
					<Path>Voices\English(UK)\start_battle_23_E843A46D.wem</Path>
				</File>
				<File Id="593410150" Language="English(UK)">
					<ShortName>start_battle_49.wav</ShortName>
					<Path>Voices\English(UK)\start_battle_49_E843A46D.wem</Path>
				</File>
				<File Id="609348742" Language="English(UK)">
					<ShortName>start_battle_54.wav</ShortName>
					<Path>Voices\English(UK)\start_battle_54_E843A46D.wem</Path>
				</File>
				<File Id="636166867" Language="English(UK)">
					<ShortName>start_battle_56.wav</ShortName>
					<Path>Voices\English(UK)\start_battle_56_E843A46D.wem</Path>
				</File>
				<File Id="641366230" Language="English(UK)">
					<ShortName>start_battle_41.wav</ShortName>
					<Path>Voices\English(UK)\start_battle_41_E843A46D.wem</Path>
				</File>
				<File Id="645039627" Language="English(UK)">
					<ShortName>surveying_devices_functional_04.wav</ShortName>
					<Path>Voices\English(UK)\surveying_devices_functional_04_E843A46D.wem</Path>
				</File>
				<File Id="679932295" Language="English(UK)">
					<ShortName>surveying_devices_functional_13.wav</ShortName>
					<Path>Voices\English(UK)\surveying_devices_functional_13_E843A46D.wem</Path>
				</File>
				<File Id="703141202" Language="English(UK)">
					<ShortName>start_battle_14.wav</ShortName>
					<Path>Voices\English(UK)\start_battle_14_E843A46D.wem</Path>
				</File>
				<File Id="706351176" Language="English(UK)">
					<ShortName>surveying_devices_functional_06.wav</ShortName>
					<Path>Voices\English(UK)\surveying_devices_functional_06_E843A46D.wem</Path>
				</File>
				<File Id="717588139" Language="English(UK)">
					<ShortName>surveying_devices_damaged_05.wav</ShortName>
					<Path>Voices\English(UK)\surveying_devices_damaged_05_E843A46D.wem</Path>
				</File>
				<File Id="754377109" Language="English(UK)">
					<ShortName>start_battle_02.wav</ShortName>
					<Path>Voices\English(UK)\start_battle_02_E843A46D.wem</Path>
				</File>
				<File Id="768515370" Language="English(UK)">
					<ShortName>start_battle_11.wav</ShortName>
					<Path>Voices\English(UK)\start_battle_11_E843A46D.wem</Path>
				</File>
				<File Id="773165737" Language="English(UK)">
					<ShortName>start_battle_20.wav</ShortName>
					<Path>Voices\English(UK)\start_battle_20_E843A46D.wem</Path>
				</File>
				<File Id="774442769" Language="English(UK)">
					<ShortName>start_battle_37.wav</ShortName>
					<Path>Voices\English(UK)\start_battle_37_E843A46D.wem</Path>
				</File>
				<File Id="784839412" Language="English(UK)">
					<ShortName>start_battle_52.wav</ShortName>
					<Path>Voices\English(UK)\start_battle_52_E843A46D.wem</Path>
				</File>
				<File Id="792533154" Language="English(UK)">
					<ShortName>start_battle_57.wav</ShortName>
					<Path>Voices\English(UK)\start_battle_57_E843A46D.wem</Path>
				</File>
				<File Id="820339774" Language="English(UK)">
					<ShortName>surveying_devices_functional_12.wav</ShortName>
					<Path>Voices\English(UK)\surveying_devices_functional_12_E843A46D.wem</Path>
				</File>
				<File Id="829496203" Language="English(UK)">
					<ShortName>start_battle_40.wav</ShortName>
					<Path>Voices\English(UK)\start_battle_40_E843A46D.wem</Path>
				</File>
				<File Id="831853501" Language="English(UK)">
					<ShortName>start_battle_09.wav</ShortName>
					<Path>Voices\English(UK)\start_battle_09_E843A46D.wem</Path>
				</File>
				<File Id="845311218" Language="English(UK)">
					<ShortName>surveying_devices_functional_07.wav</ShortName>
					<Path>Voices\English(UK)\surveying_devices_functional_07_E843A46D.wem</Path>
				</File>
				<File Id="876294971" Language="English(UK)">
					<ShortName>surveying_devices_destroyed_10.wav</ShortName>
					<Path>Voices\English(UK)\surveying_devices_destroyed_10_E843A46D.wem</Path>
				</File>
				<File Id="878327465" Language="English(UK)">
					<ShortName>start_battle_48.wav</ShortName>
					<Path>Voices\English(UK)\start_battle_48_E843A46D.wem</Path>
				</File>
				<File Id="891315615" Language="English(UK)">
					<ShortName>surveying_devices_functional_08.wav</ShortName>
					<Path>Voices\English(UK)\surveying_devices_functional_08_E843A46D.wem</Path>
				</File>
				<File Id="898814309" Language="English(UK)">
					<ShortName>start_battle_17.wav</ShortName>
					<Path>Voices\English(UK)\start_battle_17_E843A46D.wem</Path>
				</File>
				<File Id="915917319" Language="English(UK)">
					<ShortName>start_battle_44.wav</ShortName>
					<Path>Voices\English(UK)\start_battle_44_E843A46D.wem</Path>
				</File>
				<File Id="920406285" Language="English(UK)">
					<ShortName>start_battle_26.wav</ShortName>
					<Path>Voices\English(UK)\start_battle_26_E843A46D.wem</Path>
				</File>
				<File Id="923509528" Language="English(UK)">
					<ShortName>start_battle_38.wav</ShortName>
					<Path>Voices\English(UK)\start_battle_38_E843A46D.wem</Path>
				</File>
				<File Id="956301576" Language="English(UK)">
					<ShortName>start_battle_18.wav</ShortName>
					<Path>Voices\English(UK)\start_battle_18_E843A46D.wem</Path>
				</File>
				<File Id="968650227" Language="English(UK)">
					<ShortName>start_battle_28.wav</ShortName>
					<Path>Voices\English(UK)\start_battle_28_E843A46D.wem</Path>
				</File>
				<File Id="971278438" Language="English(UK)">
					<ShortName>surveying_devices_destroyed_08.wav</ShortName>
					<Path>Voices\English(UK)\surveying_devices_destroyed_08_E843A46D.wem</Path>
				</File>
				<File Id="995033085" Language="English(UK)">
					<ShortName>start_battle_01.wav</ShortName>
					<Path>Voices\English(UK)\start_battle_01_E843A46D.wem</Path>
				</File>
				<File Id="999121424" Language="English(UK)">
					<ShortName>surveying_devices_destroyed_05.wav</ShortName>
					<Path>Voices\English(UK)\surveying_devices_destroyed_05_E843A46D.wem</Path>
				</File>
				<File Id="1000817995" Language="English(UK)">
					<ShortName>start_battle_30.wav</ShortName>
					<Path>Voices\English(UK)\start_battle_30_E843A46D.wem</Path>
				</File>
				<File Id="1001044966" Language="English(UK)">
					<ShortName>start_battle_58.wav</ShortName>
					<Path>Voices\English(UK)\start_battle_58_E843A46D.wem</Path>
				</File>
				<File Id="1003526728" Language="English(UK)">
					<ShortName>start_battle_06.wav</ShortName>
					<Path>Voices\English(UK)\start_battle_06_E843A46D.wem</Path>
				</File>
				<File Id="1024034853" Language="English(UK)">
					<ShortName>surveying_devices_functional_09.wav</ShortName>
					<Path>Voices\English(UK)\surveying_devices_functional_09_E843A46D.wem</Path>
				</File>
				<File Id="1026194346" Language="English(UK)">
					<ShortName>radioman_killed_02.wav</ShortName>
					<Path>Voices\English(UK)\radioman_killed_02_E843A46D.wem</Path>
				</File>
				<File Id="1051767789" Language="English(UK)">
					<ShortName>surveying_devices_functional_14.wav</ShortName>
					<Path>Voices\English(UK)\surveying_devices_functional_14_E843A46D.wem</Path>
				</File>
				<File Id="1056649950" Language="English(UK)">
					<ShortName>start_battle_22.wav</ShortName>
					<Path>Voices\English(UK)\start_battle_22_E843A46D.wem</Path>
				</File>
				<File Id="1070082467" Language="English(UK)">
					<ShortName>radioman_killed_04.wav</ShortName>
					<Path>Voices\English(UK)\radioman_killed_04_E843A46D.wem</Path>
				</File>
			</IncludedMemoryFiles>
		</SoundBank>
		<SoundBank Id="3135547431" Language="English(US)">
			<ShortName>RelHax_3</ShortName>
			<Path>English(US)\RelHax_3.bnk</Path>
			<IncludedEvents>
				<Event Id="3928775652" Name="vo_radioman_killed"/>
				<Event Id="590598450" Name="vo_start_battle"/>
				<Event Id="2775977275" Name="vo_surveying_devices_damaged"/>
				<Event Id="1112395295" Name="vo_surveying_devices_destroyed"/>
				<Event Id="998311689" Name="vo_surveying_devices_functional"/>
			</IncludedEvents>
			<IncludedMemoryFiles>
				<File Id="7033953" Language="English(US)">
					<ShortName>start_battle_23.wav</ShortName>
					<Path>Voices\English(US)\start_battle_23_E843A46D.wem</Path>
				</File>
				<File Id="16551894" Language="English(US)">
					<ShortName>start_battle_34.wav</ShortName>
					<Path>Voices\English(US)\start_battle_34_E843A46D.wem</Path>
				</File>
				<File Id="35899331" Language="English(US)">
					<ShortName>surveying_devices_damaged_06.wav</ShortName>
					<Path>Voices\English(US)\surveying_devices_damaged_06_E843A46D.wem</Path>
				</File>
				<File Id="37667814" Language="English(US)">
					<ShortName>start_battle_18.wav</ShortName>
					<Path>Voices\English(US)\start_battle_18_E843A46D.wem</Path>
				</File>
				<File Id="41771467" Language="English(US)">
					<ShortName>start_battle_06.wav</ShortName>
					<Path>Voices\English(US)\start_battle_06_E843A46D.wem</Path>
				</File>
				<File Id="60399818" Language="English(US)">
					<ShortName>surveying_devices_functional_12.wav</ShortName>
					<Path>Voices\English(US)\surveying_devices_functional_12_E843A46D.wem</Path>
				</File>
				<File Id="61496263" Language="English(US)">
					<ShortName>start_battle_26.wav</ShortName>
					<Path>Voices\English(US)\start_battle_26_E843A46D.wem</Path>
				</File>
				<File Id="72005758" Language="English(US)">
					<ShortName>start_battle_17.wav</ShortName>
					<Path>Voices\English(US)\start_battle_17_E843A46D.wem</Path>
				</File>
				<File Id="80842302" Language="English(US)">
					<ShortName>surveying_devices_destroyed_04.wav</ShortName>
					<Path>Voices\English(US)\surveying_devices_destroyed_04_E843A46D.wem</Path>
				</File>
				<File Id="84774779" Language="English(US)">
					<ShortName>radioman_killed_02.wav</ShortName>
					<Path>Voices\English(US)\radioman_killed_02_E843A46D.wem</Path>
				</File>
				<File Id="128285174" Language="English(US)">
					<ShortName>radioman_killed_01.wav</ShortName>
					<Path>Voices\English(US)\radioman_killed_01_E843A46D.wem</Path>
				</File>
				<File Id="128615389" Language="English(US)">
					<ShortName>surveying_devices_destroyed_08.wav</ShortName>
					<Path>Voices\English(US)\surveying_devices_destroyed_08_E843A46D.wem</Path>
				</File>
				<File Id="139266316" Language="English(US)">
					<ShortName>start_battle_27.wav</ShortName>
					<Path>Voices\English(US)\start_battle_27_E843A46D.wem</Path>
				</File>
				<File Id="151319473" Language="English(US)">
					<ShortName>start_battle_33.wav</ShortName>
					<Path>Voices\English(US)\start_battle_33_E843A46D.wem</Path>
				</File>
				<File Id="185713174" Language="English(US)">
					<ShortName>surveying_devices_functional_08.wav</ShortName>
					<Path>Voices\English(US)\surveying_devices_functional_08_E843A46D.wem</Path>
				</File>
				<File Id="231924632" Language="English(US)">
					<ShortName>radioman_killed_04.wav</ShortName>
					<Path>Voices\English(US)\radioman_killed_04_E843A46D.wem</Path>
				</File>
				<File Id="269323657" Language="English(US)">
					<ShortName>start_battle_38.wav</ShortName>
					<Path>Voices\English(US)\start_battle_38_E843A46D.wem</Path>
				</File>
				<File Id="325962462" Language="English(US)">
					<ShortName>surveying_devices_damaged_03.wav</ShortName>
					<Path>Voices\English(US)\surveying_devices_damaged_03_E843A46D.wem</Path>
				</File>
				<File Id="350021997" Language="English(US)">
					<ShortName>start_battle_55.wav</ShortName>
					<Path>Voices\English(US)\start_battle_55_E843A46D.wem</Path>
				</File>
				<File Id="353076716" Language="English(US)">
					<ShortName>start_battle_46.wav</ShortName>
					<Path>Voices\English(US)\start_battle_46_E843A46D.wem</Path>
				</File>
				<File Id="354044161" Language="English(US)">
					<ShortName>start_battle_25.wav</ShortName>
					<Path>Voices\English(US)\start_battle_25_E843A46D.wem</Path>
				</File>
				<File Id="360232698" Language="English(US)">
					<ShortName>start_battle_58.wav</ShortName>
					<Path>Voices\English(US)\start_battle_58_E843A46D.wem</Path>
				</File>
				<File Id="367381372" Language="English(US)">
					<ShortName>start_battle_13.wav</ShortName>
					<Path>Voices\English(US)\start_battle_13_E843A46D.wem</Path>
				</File>
				<File Id="373270785" Language="English(US)">
					<ShortName>start_battle_37.wav</ShortName>
					<Path>Voices\English(US)\start_battle_37_E843A46D.wem</Path>
				</File>
				<File Id="384965516" Language="English(US)">
					<ShortName>start_battle_49.wav</ShortName>
					<Path>Voices\English(US)\start_battle_49_E843A46D.wem</Path>
				</File>
				<File Id="410595105" Language="English(US)">
					<ShortName>surveying_devices_functional_13.wav</ShortName>
					<Path>Voices\English(US)\surveying_devices_functional_13_E843A46D.wem</Path>
				</File>
				<File Id="434774581" Language="English(US)">
					<ShortName>start_battle_29.wav</ShortName>
					<Path>Voices\English(US)\start_battle_29_E843A46D.wem</Path>
				</File>
				<File Id="449936304" Language="English(US)">
					<ShortName>start_battle_22.wav</ShortName>
					<Path>Voices\English(US)\start_battle_22_E843A46D.wem</Path>
				</File>
				<File Id="451502154" Language="English(US)">
					<ShortName>start_battle_02.wav</ShortName>
					<Path>Voices\English(US)\start_battle_02_E843A46D.wem</Path>
				</File>
				<File Id="454008035" Language="English(US)">
					<ShortName>start_battle_45.wav</ShortName>
					<Path>Voices\English(US)\start_battle_45_E843A46D.wem</Path>
				</File>
				<File Id="474290093" Language="English(US)">
					<ShortName>start_battle_56.wav</ShortName>
					<Path>Voices\English(US)\start_battle_56_E843A46D.wem</Path>
				</File>
				<File Id="503764963" Language="English(US)">
					<ShortName>surveying_devices_damaged_04.wav</ShortName>
					<Path>Voices\English(US)\surveying_devices_damaged_04_E843A46D.wem</Path>
				</File>
				<File Id="521641112" Language="English(US)">
					<ShortName>surveying_devices_damaged_01.wav</ShortName>
					<Path>Voices\English(US)\surveying_devices_damaged_01_E843A46D.wem</Path>
				</File>
				<File Id="542358087" Language="English(US)">
					<ShortName>surveying_devices_destroyed_02.wav</ShortName>
					<Path>Voices\English(US)\surveying_devices_destroyed_02_E843A46D.wem</Path>
				</File>
				<File Id="545313643" Language="English(US)">
					<ShortName>start_battle_04.wav</ShortName>
					<Path>Voices\English(US)\start_battle_04_E843A46D.wem</Path>
				</File>
				<File Id="547129249" Language="English(US)">
					<ShortName>start_battle_03.wav</ShortName>
					<Path>Voices\English(US)\start_battle_03_E843A46D.wem</Path>
				</File>
				<File Id="552990002" Language="English(US)">
					<ShortName>start_battle_40.wav</ShortName>
					<Path>Voices\English(US)\start_battle_40_E843A46D.wem</Path>
				</File>
				<File Id="574925235" Language="English(US)">
					<ShortName>surveying_devices_functional_02.wav</ShortName>
					<Path>Voices\English(US)\surveying_devices_functional_02_E843A46D.wem</Path>
				</File>
				<File Id="577039865" Language="English(US)">
					<ShortName>surveying_devices_functional_11.wav</ShortName>
					<Path>Voices\English(US)\surveying_devices_functional_11_E843A46D.wem</Path>
				</File>
				<File Id="606533160" Language="English(US)">
					<ShortName>surveying_devices_functional_10.wav</ShortName>
					<Path>Voices\English(US)\surveying_devices_functional_10_E843A46D.wem</Path>
				</File>
				<File Id="610866861" Language="English(US)">
					<ShortName>start_battle_47.wav</ShortName>
					<Path>Voices\English(US)\start_battle_47_E843A46D.wem</Path>
				</File>
				<File Id="613135343" Language="English(US)">
					<ShortName>surveying_devices_functional_07.wav</ShortName>
					<Path>Voices\English(US)\surveying_devices_functional_07_E843A46D.wem</Path>
				</File>
				<File Id="621431405" Language="English(US)">
					<ShortName>surveying_devices_destroyed_10.wav</ShortName>
					<Path>Voices\English(US)\surveying_devices_destroyed_10_E843A46D.wem</Path>
				</File>
				<File Id="623969336" Language="English(US)">
					<ShortName>start_battle_21.wav</ShortName>
					<Path>Voices\English(US)\start_battle_21_E843A46D.wem</Path>
				</File>
				<File Id="624849274" Language="English(US)">
					<ShortName>start_battle_41.wav</ShortName>
					<Path>Voices\English(US)\start_battle_41_E843A46D.wem</Path>
				</File>
				<File Id="625410069" Language="English(US)">
					<ShortName>start_battle_10.wav</ShortName>
					<Path>Voices\English(US)\start_battle_10_E843A46D.wem</Path>
				</File>
				<File Id="633462547" Language="English(US)">
					<ShortName>start_battle_12.wav</ShortName>
					<Path>Voices\English(US)\start_battle_12_E843A46D.wem</Path>
				</File>
				<File Id="638578269" Language="English(US)">
					<ShortName>radioman_killed_03.wav</ShortName>
					<Path>Voices\English(US)\radioman_killed_03_E843A46D.wem</Path>
				</File>
				<File Id="661854028" Language="English(US)">
					<ShortName>surveying_devices_functional_09.wav</ShortName>
					<Path>Voices\English(US)\surveying_devices_functional_09_E843A46D.wem</Path>
				</File>
				<File Id="664638246" Language="English(US)">
					<ShortName>start_battle_01.wav</ShortName>
					<Path>Voices\English(US)\start_battle_01_E843A46D.wem</Path>
				</File>
				<File Id="684738324" Language="English(US)">
					<ShortName>start_battle_36.wav</ShortName>
					<Path>Voices\English(US)\start_battle_36_E843A46D.wem</Path>
				</File>
				<File Id="700931911" Language="English(US)">
					<ShortName>start_battle_07.wav</ShortName>
					<Path>Voices\English(US)\start_battle_07_E843A46D.wem</Path>
				</File>
				<File Id="703629826" Language="English(US)">
					<ShortName>start_battle_57.wav</ShortName>
					<Path>Voices\English(US)\start_battle_57_E843A46D.wem</Path>
				</File>
				<File Id="704022739" Language="English(US)">
					<ShortName>start_battle_50.wav</ShortName>
					<Path>Voices\English(US)\start_battle_50_E843A46D.wem</Path>
				</File>
				<File Id="726862494" Language="English(US)">
					<ShortName>surveying_devices_functional_01.wav</ShortName>
					<Path>Voices\English(US)\surveying_devices_functional_01_E843A46D.wem</Path>
				</File>
				<File Id="730085633" Language="English(US)">
					<ShortName>start_battle_09.wav</ShortName>
					<Path>Voices\English(US)\start_battle_09_E843A46D.wem</Path>
				</File>
				<File Id="738793494" Language="English(US)">
					<ShortName>start_battle_15.wav</ShortName>
					<Path>Voices\English(US)\start_battle_15_E843A46D.wem</Path>
				</File>
				<File Id="739064629" Language="English(US)">
					<ShortName>start_battle_11.wav</ShortName>
					<Path>Voices\English(US)\start_battle_11_E843A46D.wem</Path>
				</File>
				<File Id="739579212" Language="English(US)">
					<ShortName>start_battle_20.wav</ShortName>
					<Path>Voices\English(US)\start_battle_20_E843A46D.wem</Path>
				</File>
				<File Id="739969899" Language="English(US)">
					<ShortName>start_battle_54.wav</ShortName>
					<Path>Voices\English(US)\start_battle_54_E843A46D.wem</Path>
				</File>
				<File Id="753346479" Language="English(US)">
					<ShortName>surveying_devices_destroyed_05.wav</ShortName>
					<Path>Voices\English(US)\surveying_devices_destroyed_05_E843A46D.wem</Path>
				</File>
				<File Id="757698949" Language="English(US)">
					<ShortName>start_battle_30.wav</ShortName>
					<Path>Voices\English(US)\start_battle_30_E843A46D.wem</Path>
				</File>
				<File Id="760337569" Language="English(US)">
					<ShortName>start_battle_05.wav</ShortName>
					<Path>Voices\English(US)\start_battle_05_E843A46D.wem</Path>
				</File>
				<File Id="760627348" Language="English(US)">
					<ShortName>start_battle_42.wav</ShortName>
					<Path>Voices\English(US)\start_battle_42_E843A46D.wem</Path>
				</File>
				<File Id="768648927" Language="English(US)">
					<ShortName>surveying_devices_destroyed_01.wav</ShortName>
					<Path>Voices\English(US)\surveying_devices_destroyed_01_E843A46D.wem</Path>
				</File>
				<File Id="771621818" Language="English(US)">
					<ShortName>start_battle_35.wav</ShortName>
					<Path>Voices\English(US)\start_battle_35_E843A46D.wem</Path>
				</File>
				<File Id="775774545" Language="English(US)">
					<ShortName>surveying_devices_functional_05.wav</ShortName>
					<Path>Voices\English(US)\surveying_devices_functional_05_E843A46D.wem</Path>
				</File>
				<File Id="777029712" Language="English(US)">
					<ShortName>surveying_devices_damaged_07.wav</ShortName>
					<Path>Voices\English(US)\surveying_devices_damaged_07_E843A46D.wem</Path>
				</File>
				<File Id="781393392" Language="English(US)">
					<ShortName>start_battle_39.wav</ShortName>
					<Path>Voices\English(US)\start_battle_39_E843A46D.wem</Path>
				</File>
				<File Id="783870646" Language="English(US)">
					<ShortName>start_battle_44.wav</ShortName>
					<Path>Voices\English(US)\start_battle_44_E843A46D.wem</Path>
				</File>
				<File Id="795479813" Language="English(US)">
					<ShortName>start_battle_51.wav</ShortName>
					<Path>Voices\English(US)\start_battle_51_E843A46D.wem</Path>
				</File>
				<File Id="805759074" Language="English(US)">
					<ShortName>start_battle_08.wav</ShortName>
					<Path>Voices\English(US)\start_battle_08_E843A46D.wem</Path>
				</File>
				<File Id="809009919" Language="English(US)">
					<ShortName>start_battle_24.wav</ShortName>
					<Path>Voices\English(US)\start_battle_24_E843A46D.wem</Path>
				</File>
				<File Id="812612622" Language="English(US)">
					<ShortName>surveying_devices_functional_06.wav</ShortName>
					<Path>Voices\English(US)\surveying_devices_functional_06_E843A46D.wem</Path>
				</File>
				<File Id="812941987" Language="English(US)">
					<ShortName>surveying_devices_destroyed_06.wav</ShortName>
					<Path>Voices\English(US)\surveying_devices_destroyed_06_E843A46D.wem</Path>
				</File>
				<File Id="818566916" Language="English(US)">
					<ShortName>start_battle_31.wav</ShortName>
					<Path>Voices\English(US)\start_battle_31_E843A46D.wem</Path>
				</File>
				<File Id="843626974" Language="English(US)">
					<ShortName>start_battle_28.wav</ShortName>
					<Path>Voices\English(US)\start_battle_28_E843A46D.wem</Path>
				</File>
				<File Id="850034347" Language="English(US)">
					<ShortName>start_battle_16.wav</ShortName>
					<Path>Voices\English(US)\start_battle_16_E843A46D.wem</Path>
				</File>
				<File Id="851279803" Language="English(US)">
					<ShortName>surveying_devices_functional_14.wav</ShortName>
					<Path>Voices\English(US)\surveying_devices_functional_14_E843A46D.wem</Path>
				</File>
				<File Id="852649397" Language="English(US)">
					<ShortName>surveying_devices_destroyed_07.wav</ShortName>
					<Path>Voices\English(US)\surveying_devices_destroyed_07_E843A46D.wem</Path>
				</File>
				<File Id="886558866" Language="English(US)">
					<ShortName>surveying_devices_functional_03.wav</ShortName>
					<Path>Voices\English(US)\surveying_devices_functional_03_E843A46D.wem</Path>
				</File>
				<File Id="916610720" Language="English(US)">
					<ShortName>start_battle_19.wav</ShortName>
					<Path>Voices\English(US)\start_battle_19_E843A46D.wem</Path>
				</File>
				<File Id="918373617" Language="English(US)">
					<ShortName>start_battle_32.wav</ShortName>
					<Path>Voices\English(US)\start_battle_32_E843A46D.wem</Path>
				</File>
				<File Id="922939990" Language="English(US)">
					<ShortName>surveying_devices_damaged_08.wav</ShortName>
					<Path>Voices\English(US)\surveying_devices_damaged_08_E843A46D.wem</Path>
				</File>
				<File Id="924838754" Language="English(US)">
					<ShortName>start_battle_52.wav</ShortName>
					<Path>Voices\English(US)\start_battle_52_E843A46D.wem</Path>
				</File>
				<File Id="951536117" Language="English(US)">
					<ShortName>start_battle_48.wav</ShortName>
					<Path>Voices\English(US)\start_battle_48_E843A46D.wem</Path>
				</File>
				<File Id="983315764" Language="English(US)">
					<ShortName>start_battle_43.wav</ShortName>
					<Path>Voices\English(US)\start_battle_43_E843A46D.wem</Path>
				</File>
				<File Id="1001377416" Language="English(US)">
					<ShortName>surveying_devices_destroyed_09.wav</ShortName>
					<Path>Voices\English(US)\surveying_devices_destroyed_09_E843A46D.wem</Path>
				</File>
				<File Id="1009664014" Language="English(US)">
					<ShortName>start_battle_53.wav</ShortName>
					<Path>Voices\English(US)\start_battle_53_E843A46D.wem</Path>
				</File>
				<File Id="1014510790" Language="English(US)">
					<ShortName>surveying_devices_functional_04.wav</ShortName>
					<Path>Voices\English(US)\surveying_devices_functional_04_E843A46D.wem</Path>
				</File>
				<File Id="1037544457" Language="English(US)">
					<ShortName>surveying_devices_damaged_05.wav</ShortName>
					<Path>Voices\English(US)\surveying_devices_damaged_05_E843A46D.wem</Path>
				</File>
				<File Id="1039650735" Language="English(US)">
					<ShortName>surveying_devices_destroyed_03.wav</ShortName>
					<Path>Voices\English(US)\surveying_devices_destroyed_03_E843A46D.wem</Path>
				</File>
				<File Id="1039848926" Language="English(US)">
					<ShortName>start_battle_14.wav</ShortName>
					<Path>Voices\English(US)\start_battle_14_E843A46D.wem</Path>
				</File>
				<File Id="1061309795" Language="English(US)">
					<ShortName>surveying_devices_damaged_02.wav</ShortName>
					<Path>Voices\English(US)\surveying_devices_damaged_02_E843A46D.wem</Path>
				</File>
			</IncludedMemoryFiles>
		</SoundBank>
	</SoundBanks>
</SoundBanksInfo>
